.coveragerc
.gitignore
CMakeLists.txt
LICENSE
MANIFEST.in
README.md
setup.cfg
setup.py
.github/workflows/building-conda.yml
.github/workflows/building.yml
.github/workflows/linting.yml
.github/workflows/stale.yml
.github/workflows/testing.yml
.github/workflows/cuda/cu101-Linux-env.sh
.github/workflows/cuda/cu101-Linux.sh
.github/workflows/cuda/cu101-Windows-env.sh
.github/workflows/cuda/cu101-Windows.sh
.github/workflows/cuda/cu102-Linux-env.sh
.github/workflows/cuda/cu102-Linux.sh
.github/workflows/cuda/cu102-Windows-env.sh
.github/workflows/cuda/cu102-Windows.sh
.github/workflows/cuda/cu111-Linux-env.sh
.github/workflows/cuda/cu111-Linux.sh
.github/workflows/cuda/cu111-Windows-env.sh
.github/workflows/cuda/cu111-Windows.sh
.github/workflows/cuda/cu113-Linux-env.sh
.github/workflows/cuda/cu113-Linux.sh
.github/workflows/cuda/cu113-Windows-env.sh
.github/workflows/cuda/cu113-Windows.sh
.github/workflows/cuda/cu115-Linux-env.sh
.github/workflows/cuda/cu115-Linux.sh
.github/workflows/cuda/cu115-Windows-env.sh
.github/workflows/cuda/cu115-Windows.sh
.github/workflows/cuda/cu116-Linux-env.sh
.github/workflows/cuda/cu116-Linux.sh
.github/workflows/cuda/cu116-Windows-env.sh
.github/workflows/cuda/cu116-Windows.sh
.github/workflows/cuda/cu117-Linux-env.sh
.github/workflows/cuda/cu117-Linux.sh
.github/workflows/cuda/cu117-Windows-env.sh
.github/workflows/cuda/cu117-Windows.sh
.github/workflows/cuda/cu118-Linux-env.sh
.github/workflows/cuda/cu118-Linux.sh
.github/workflows/cuda/cu118-Windows-env.sh
.github/workflows/cuda/cu118-Windows.sh
cmake/TorchSplineConvConfig.cmake.in
conda/pytorch-spline-conv/README.md
conda/pytorch-spline-conv/build_conda.sh
conda/pytorch-spline-conv/meta.yaml
csrc/basis.cpp
csrc/spline_conv.h
csrc/version.cpp
csrc/weighting.cpp
csrc/cpu/basis_cpu.cpp
csrc/cpu/basis_cpu.h
csrc/cpu/utils.h
csrc/cpu/weighting_cpu.cpp
csrc/cpu/weighting_cpu.h
csrc/cuda/atomics.cuh
csrc/cuda/basis_cuda.cu
csrc/cuda/basis_cuda.h
csrc/cuda/utils.cuh
torch_spline_conv.egg-info/PKG-INFO
torch_spline_conv.egg-info/SOURCES.txt
torch_spline_conv.egg-info/dependency_links.txt
torch_spline_conv.egg-info/requires.txt
torch_spline_conv.egg-info/top_level.txt