Metadata-Version: 2.1
Name: torch-spline-conv
Version: 1.2.2
Summary: Implementation of the Spline-Based Convolution Operator of SplineCNN in PyTorch
Home-page: https://github.com/rusty1s/pytorch_spline_conv
Download-URL: https://github.com/rusty1s/pytorch_spline_conv/archive/1.2.2.tar.gz
Author: Matthias Fey
Author-email: matthias.fey@tu-dortmund.de
License: UNKNOWN
Keywords: pytorch,geometric-deep-learning,graph-neural-networks,spline-cnn
Platform: UNKNOWN
Classifier: Development Status :: 5 - Production/Stable
Classifier: License :: OSI Approved :: MIT License
Classifier: Programming Language :: Python
Classifier: Programming Language :: Python :: 3.7
Classifier: Programming Language :: Python :: 3.8
Classifier: Programming Language :: Python :: 3.9
Classifier: Programming Language :: Python :: 3.10
Classifier: Programming Language :: Python :: 3 :: Only
Requires-Python: >=3.7
Provides-Extra: test
License-File: LICENSE
